lqs_client/__init__.py
lqs_client/__main__.py
lqs_client/definitions/__init__.py
lqs_client/definitions/actionlib_msgs/msg/GoalID.msg
lqs_client/definitions/actionlib_msgs/msg/GoalStatus.msg
lqs_client/definitions/actionlib_msgs/msg/GoalStatusArray.msg
lqs_client/definitions/diagnostic_msgs/msg/DiagnosticArray.msg
lqs_client/definitions/diagnostic_msgs/msg/DiagnosticStatus.msg
lqs_client/definitions/diagnostic_msgs/msg/KeyValue.msg
lqs_client/definitions/geometry_msgs/msg/Accel.msg
lqs_client/definitions/geometry_msgs/msg/AccelStamped.msg
lqs_client/definitions/geometry_msgs/msg/AccelWithCovariance.msg
lqs_client/definitions/geometry_msgs/msg/AccelWithCovarianceStamped.msg
lqs_client/definitions/geometry_msgs/msg/Inertia.msg
lqs_client/definitions/geometry_msgs/msg/InertiaStamped.msg
lqs_client/definitions/geometry_msgs/msg/Point.msg
lqs_client/definitions/geometry_msgs/msg/Point32.msg
lqs_client/definitions/geometry_msgs/msg/PointStamped.msg
lqs_client/definitions/geometry_msgs/msg/Polygon.msg
lqs_client/definitions/geometry_msgs/msg/PolygonStamped.msg
lqs_client/definitions/geometry_msgs/msg/Pose.msg
lqs_client/definitions/geometry_msgs/msg/Pose2D.msg
lqs_client/definitions/geometry_msgs/msg/PoseArray.msg
lqs_client/definitions/geometry_msgs/msg/PoseStamped.msg
lqs_client/definitions/geometry_msgs/msg/PoseWithCovariance.msg
lqs_client/definitions/geometry_msgs/msg/PoseWithCovarianceStamped.msg
lqs_client/definitions/geometry_msgs/msg/Quaternion.msg
lqs_client/definitions/geometry_msgs/msg/QuaternionStamped.msg
lqs_client/definitions/geometry_msgs/msg/Transform.msg
lqs_client/definitions/geometry_msgs/msg/TransformStamped.msg
lqs_client/definitions/geometry_msgs/msg/Twist.msg
lqs_client/definitions/geometry_msgs/msg/TwistStamped.msg
lqs_client/definitions/geometry_msgs/msg/TwistWithCovariance.msg
lqs_client/definitions/geometry_msgs/msg/TwistWithCovarianceStamped.msg
lqs_client/definitions/geometry_msgs/msg/Vector3.msg
lqs_client-0.1.13.dist-info/METADATA
lqs_client-0.1.13.dist-info/WHEEL
lqs_client-0.1.13.dist-info/top_level.txt
lqs_client-0.1.13.dist-info/RECORD
