Metadata-Version: 2.1
Name: lqs-client
Version: 0.1.13
Summary: LogQS Client
Home-page: https://github.com/carnegierobotics/LogQS-Client
Author: Nathan Margaglio
Author-email: nmargaglio@carnegierobotics.com
Project-URL: Bug Tracker, https://github.com/carnegierobotics/LogQS-Client/issues
Classifier: Programming Language :: Python :: 3
Classifier: License :: OSI Approved :: MIT License
Classifier: Operating System :: OS Independent
Requires-Python: >=3.6
Requires-Dist: fire <1.0,>=0.4.0
Requires-Dist: python-dotenv <1.0,>=0.0
Requires-Dist: requests <3.0,>=2.0
Requires-Dist: xmltodict <1.0.0,>=0.13.0
Requires-Dist: py3rosmsgs <2.0.0,>=1.18.0
Requires-Dist: rospkg <2.0.0,>=1.4.0
Requires-Dist: tqdm <5.0,>=4.0
Requires-Dist: boto3 <2.0.0,>=1.26.0
Requires-Dist: Pillow <11.0.0,==10.0.0
Requires-Dist: numpy <2.0.0,>=1.22.0
Requires-Dist: lz4 <5.0.0,>=4.0.0
Requires-Dist: zstd <2.0.0,>=1.5.0
Requires-Dist: s3path <1.0.0,>=0.4.0
